<?xml version="1.0" encoding="UTF-8"?>
<!DOCTYPE nmaprun>
<?xml-stylesheet href="file:///usr/bin/../share/nmap/nmap.xsl" type="text/xsl"?>
<!-- Nmap 7.12 scan initiated Fri Jul 15 12:47:39 2016 as: nmap -Pn -n -sS -p 21-23,25,53,111,137,139,445,80,443,8443,8080 -&#45;min-hostgroup 255 -&#45;min-rtt-timeout 0ms -&#45;max-rtt-timeout 100ms -&#45;max-retries 1 -&#45;max-scan-delay 0 -&#45;min-rate 6000 -oA CLIENT-# -vvv -&#45;open 192.168.0.1-254 -->
<nmaprun scanner="nmap" args="nmap -Pn -n -sS -p 21-23,25,53,111,137,139,445,80,443,8443,8080 -&#45;min-hostgroup 255 -&#45;min-rtt-timeout 0ms -&#45;max-rtt-timeout 100ms -&#45;max-retries 1 -&#45;max-scan-delay 0 -&#45;min-rate 6000 -oA CLIENT-# -vvv -&#45;open 192.168.0.1-254" start="1468583259" startstr="Fri Jul 15 12:47:39 2016" version="7.12" xmloutputversion="1.04">
<scaninfo type="syn" protocol="tcp" numservices="13" services="21-23,25,53,80,111,137,139,443,445,8080,8443"/>
<verbose level="3"/>
<debugging level="0"/>
<taskbegin task="ARP Ping Scan" time="1468583259"/>
<taskend task="ARP Ping Scan" time="1468583260" extrainfo="253 total hosts"/>
<taskbegin task="SYN Stealth Scan" time="1468583260"/>
<taskend task="SYN Stealth Scan" time="1468583260" extrainfo="26 total ports"/>
<taskbegin task="SYN Stealth Scan" time="1468583260"/>
<taskend task="SYN Stealth Scan" time="1468583260" extrainfo="13 total ports"/>
<host starttime="1468583260" endtime="1468583260"><status state="up" reason="user-set" reason_ttl="0"/>
<address addr="192.168.0.7" addrtype="ipv4"/>
<hostnames>
</hostnames>
<ports><extraports state="closed" count="10">
<extrareasons reason="resets" count="10"/>
</extraports>
<port protocol="tcp" portid="80"><state state="open" reason="syn-ack" reason_ttl="64"/><service name="http" method="table" conf="3"/></port>
<port protocol="tcp" portid="111"><state state="open" reason="syn-ack" reason_ttl="64"/><service name="rpcbind" method="table" conf="3"/></port>
<port protocol="tcp" portid="443"><state state="open" reason="syn-ack" reason_ttl="64"/><service name="https" method="table" conf="3"/></port>
</ports>
<times srtt="13" rttvar="165" to="673"/>
</host>
<runstats><finished time="1468583260" timestr="Fri Jul 15 12:47:40 2016" elapsed="0.64" summary="Nmap done at Fri Jul 15 12:47:40 2016; 254 IP addresses (3 hosts up) scanned in 0.64 seconds" exit="success"/><hosts up="3" down="251" total="254"/>
</runstats>
</nmaprun>
